[
    {
        "order_number": "000000002",
        "status": "Pending",
        "items": [
            {
                "name": "Brioche",
                "price": 120,
                "image": "http:\/\/localhost\/palbites\/data\/uploads\/1741914523_brioche.svg",
                "quantity": 1
            }
        ],
        "date": "2025-03-14 06:42:16",
        "shipped_date": null
    },
    {
        "order_number": "000000003",
        "status": "Pending",
        "items": [
            {
                "name": "Brownies",
                "price": 70,
                "image": "http:\/\/localhost\/palbites\/data\/uploads\/1741914544_brownies.svg",
                "quantity": 4
            }
        ],
        "date": "2025-03-14 06:44:59",
        "shipped_date": null
    },
    {
        "order_number": "000000009",
        "status": "Pending",
        "items": [
            {
                "name": "Baguette",
                "price": 90,
                "image": "http:\/\/localhost\/palbites\/data\/uploads\/1741914503_baguette.svg",
                "quantity": 5
            },
            {
                "name": "Brownies",
                "price": 70,
                "image": "http:\/\/localhost\/palbites\/data\/uploads\/1741914544_brownies.svg",
                "quantity": 1
            }
        ],
        "date": "2025-03-14 09:56:40",
        "shipped_date": null
    }
]